Metadata-Version: 2.1
Name: swapchat
Version: 0.0.2
Summary: SwapChat Python Library
Home-page: https://github.com/Generative-Labs/SwapChat-SDK-Python
Author: SwapChat
Author-email: SwapChat@housechan.com
License: MIT
Project-URL: Website, https://github.com/Generative-Labs/SwapChat-SDK-Python
Keywords: SwapChat python sdk
Platform: UNKNOWN
Classifier: Development Status :: 3 - Alpha
Classifier: Programming Language :: Python
Classifier: Programming Language :: Python :: 3.6
Classifier: Intended Audience :: Developers
Classifier: License :: OSI Approved :: MIT License
Classifier: Operating System :: OS Independent
Requires-Python: >=3.6
